tkp_utils/__init__.py
tkp_utils/_version.py
tkp_utils/web.py
tkp_utils/assets/static/css/font-awesome.min.css
tkp_utils/assets/static/fonts/fontawesome-webfont.woff
tkp_utils/assets/static/fonts/fontawesome-webfont.woff2
tkp_utils/assets/static/img/fb.svg
tkp_utils/assets/static/img/in.svg
tkp_utils/assets/static/img/tw.svg
tkp_utils/assets/templates/404.html
tkp_utils/assets/templates/home.html
tkp_utils/assets/templates/index.html
tkp_utils/sqla/__init__.py
tkp_utils/sqla/fixtures.py
tkp_utils/sqla/models.py
tkp_utils/tests/__init__.py
tkp_utils/tests/test_all.py
tkp_utils/tests/test_utils.py
tkp_utils/tests/test_handlers/__init__.py
tkp_utils/tests/test_handlers/test_base.py
tkp_utils/tests/test_handlers/test_html.py
tkp_utils/tests/test_handlers/test_login.py
tkp_utils/tests/test_handlers/test_logout.py
tkp_utils/tornado/__init__.py
tkp_utils/tornado/handlers/__init__.py
tkp_utils/tornado/handlers/base.py
tkp_utils/tornado/handlers/html.py
tkp_utils/tornado/handlers/login.py
tkp_utils/tornado/handlers/register.py
tkp_utils-0.1.5.dist-info/LICENSE
tkp_utils-0.1.5.dist-info/METADATA
tkp_utils-0.1.5.dist-info/WHEEL
tkp_utils-0.1.5.dist-info/top_level.txt
tkp_utils-0.1.5.dist-info/RECORD
